pyprobe/__init__.py
pyprobe/_version.py
pyprobe/cell.py
pyprobe/dashboard.py
pyprobe/filters.py
pyprobe/plot.py
pyprobe/pyprobe_types.py
pyprobe/rawdata.py
pyprobe/readme_processor.py
pyprobe/result.py
pyprobe/units.py
pyprobe/utils.py
pyprobe/analysis/__init__.py
pyprobe/analysis/cycling.py
pyprobe/analysis/degradation_mode_analysis.py
pyprobe/analysis/differentiation.py
pyprobe/analysis/pulsing.py
pyprobe/analysis/smoothing.py
pyprobe/analysis/time_series.py
pyprobe/analysis/utils.py
pyprobe/analysis/base/__init__.py
pyprobe/analysis/base/degradation_mode_analysis_functions.py
pyprobe/analysis/base/differentiation_functions.py
pyprobe/cyclers/__init__.py
pyprobe/cyclers/arbin.py
pyprobe/cyclers/basecycler.py
pyprobe/cyclers/basytec.py
pyprobe/cyclers/biologic.py
pyprobe/cyclers/column_maps.py
pyprobe/cyclers/maccor.py
pyprobe/cyclers/neware.py
pyprobe/cyclers/novonix.py
pyprobe_data-2.5.0.dist-info/METADATA
pyprobe_data-2.5.0.dist-info/WHEEL
pyprobe_data-2.5.0.dist-info/licenses/LICENSE
pyprobe_data-2.5.0.dist-info/RECORD
