Metadata-Version: 2.4
Name: PyProBE-Data
Version: 2.5.0
Project-URL: Homepage, https://github.com/ImperialCollegeLondon/PyProBE
Project-URL: Documentation, https://https://pyprobe.readthedocs.io/PyProBE/
Project-URL: Repository, https://github.com/ImperialCollegeLondon/PyProBE
Project-URL: Releases, https://github.com/ImperialCollegeLondon/PyProBE/releases
Project-URL: Changelog, https://github.com/ImperialCollegeLondon/PyProBE/blob/main/CHANGELOG.md
Author: Thomas Holland
License: BSD 3-Clause License
License-File: LICENSE
Classifier: Intended Audience :: Science/Research
Classifier: License :: OSI Approved :: BSD License
Classifier: Programming Language :: Python
Classifier: Programming Language :: Python :: 3
Classifier: Programming Language :: Python :: 3 :: Only
Classifier: Programming Language :: Python :: 3.11
Classifier: Programming Language :: Python :: 3.12
Classifier: Topic :: Scientific/Engineering
Requires-Python: <3.13,>=3.11
Requires-Dist: distinctipy>=1.3.4
Requires-Dist: fastexcel>=0.12.0
Requires-Dist: ipykernel>=6.29.5
Requires-Dist: joblib>=1.4.2
Requires-Dist: loguru>=0.7.3
Requires-Dist: matplotlib>=3.10.0
Requires-Dist: numpy>=1.26.4
Requires-Dist: pandas>=2.2.3
Requires-Dist: plotly>=5.24.1
Requires-Dist: polars>=1.18.0
Requires-Dist: pydantic>=2.10.4
Requires-Dist: pyyaml>=6.0.2
Requires-Dist: scikit-learn>=1.6.0
Requires-Dist: streamlit>=1.41.1
Requires-Dist: sympy>=1.13.3
Requires-Dist: tzlocal>=5.2
Provides-Extra: dev
Requires-Dist: nbmake>=1.5.5; extra == 'dev'
Requires-Dist: pre-commit>=4.0.1; extra == 'dev'
Requires-Dist: pytest-benchmark>=5.1.0; extra == 'dev'
Requires-Dist: pytest-cov>=6.0.0; extra == 'dev'
Requires-Dist: pytest-mock>=3.14.0; extra == 'dev'
Requires-Dist: pytest-xdist>=3.6.1; extra == 'dev'
Requires-Dist: pytest>=8.3.4; extra == 'dev'
Requires-Dist: python-semantic-release>=9.15.2; extra == 'dev'
Requires-Dist: xlsxwriter>=3.2.0; extra == 'dev'
Provides-Extra: docs
Requires-Dist: myst-nb>=1.2.0; extra == 'docs'
Requires-Dist: pydata-sphinx-theme>=0.16.1; extra == 'docs'
Requires-Dist: sphinx-design>=0.6.1; extra == 'docs'
Requires-Dist: sphinx-tabs>=3.4.7; extra == 'docs'
Requires-Dist: sphinx>=7.2.6; extra == 'docs'
Requires-Dist: sphinxcontrib-bibtex>=2.6.3; extra == 'docs'
Provides-Extra: hvplot
Requires-Dist: hvplot>=0.11.2; extra == 'hvplot'
Provides-Extra: pybamm
Requires-Dist: pybamm[cite]>=25.1.1; extra == 'pybamm'
Provides-Extra: seaborn
Requires-Dist: seaborn>=0.13.2; extra == 'seaborn'
